ugctools/__init__.py
ugctools/cli.py
ugctools/redbook/__init__.py
ugctools/redbook/news/__init__.py
ugctools/redbook/news/cfg.json
ugctools/redbook/news/default/admonition.css
ugctools/redbook/news/default/default.tpl
ugctools/redbook/news/default/example.md
ugctools/redbook/news/default/page-0.tpl
ugctools/redbook/news/default/prism.css
ugctools/redbook/news/default/prism.js
ugctools/redbook/news/default/style.css
ugctools/redbook/news/seven/admonition.css
ugctools/redbook/news/seven/default.tpl
ugctools/redbook/news/seven/example.md
ugctools/redbook/news/seven/page-2.jpeg
ugctools/redbook/news/seven/page-3.jpeg
ugctools/redbook/news/seven/paper-1.jpeg
ugctools/redbook/news/seven/prism.css
ugctools/redbook/news/seven/prism.js
ugctools/redbook/news/seven/shade-1.jpeg
ugctools/redbook/news/seven/shade-2.jpeg
ugctools/redbook/news/seven/shade-3.jpeg
ugctools/redbook/news/seven/shade-4.jpeg
ugctools/redbook/news/seven/shade-5.jpeg
ugctools/redbook/news/seven/shade-6.jpeg
ugctools/redbook/news/seven/style.css
ugctools/server.py
ugctools/util.py
ugctools-0.3.0.dist-info/LICENSE
ugctools-0.3.0.dist-info/METADATA
ugctools-0.3.0.dist-info/WHEEL
ugctools-0.3.0.dist-info/entry_points.txt
ugctools-0.3.0.dist-info/RECORD
