Metadata-Version: 2.1
Name: ugctools
Version: 0.3.0
Summary: 
Author: aaron yang
Author-email: aaron_yang@jieyu.ai
Requires-Python: >=3.8,<4.0
Classifier: Programming Language :: Python :: 3
Classifier: Programming Language :: Python :: 3.8
Classifier: Programming Language :: Python :: 3.9
Classifier: Programming Language :: Python :: 3.10
Classifier: Programming Language :: Python :: 3.11
Requires-Dist: PyMuPDF (>=1.21.1,<2.0.0)
Requires-Dist: arrow (>=1.2.3,<2.0.0)
Requires-Dist: fire (>=0.5.0,<0.6.0)
Requires-Dist: markdown (>=3.4.3,<4.0.0)
Requires-Dist: weasyprint (>=58.1,<59.0)
